france_political_plots/__init__.py
france_political_plots/cli.py
france_political_plots/config.toml
france_political_plots/data/__init__.py
france_political_plots/data/government_spending.py
france_political_plots/server/__init__.py
france_political_plots/server/assets/volt-data-250x250.jpeg
france_political_plots/server/assets/volt-data-250x250.png
france_political_plots/server/assets/volt-data-250x250.webp
france_political_plots/server/assets/volt-data-500x500.jpeg
france_political_plots/server/assets/volt-data-500x500.png
france_political_plots/server/assets/volt-data-500x500.webp
france_political_plots/server/assets/volt-data-750x750.jpeg
france_political_plots/server/assets/volt-data-750x750.png
france_political_plots/server/assets/volt-data-750x750.webp
france_political_plots/server/assets/volt-data.ico
france_political_plots/server/assets/volt-data.svg
france_political_plots/server/government_spending.py
france_political_plots/server/polling_stations.py
france_political_plots/utils.py
france_political_plots-0.1.1.dist-info/METADATA
france_political_plots-0.1.1.dist-info/WHEEL
france_political_plots-0.1.1.dist-info/entry_points.txt
france_political_plots-0.1.1.dist-info/RECORD
