Metadata-Version: 2.1
Name: france-political-plots
Version: 0.1.1
Summary: 
Author: Your Name
Author-email: you@example.com
Requires-Python: >=3.11,<4.0
Classifier: Programming Language :: Python :: 3
Classifier: Programming Language :: Python :: 3.11
Requires-Dist: dash (>=2.11.1,<3.0.0)
Requires-Dist: dash-ag-grid (>=2.2.0,<3.0.0)
Requires-Dist: dash-iconify (>=0.1.2,<0.2.0)
Requires-Dist: dash-mantine-components (>=0.12.1,<0.13.0)
Requires-Dist: eurostat (>=1.0.4,<2.0.0)
Requires-Dist: gunicorn (>=21.1.0,<22.0.0)
Requires-Dist: pandas (>=2.0.3,<3.0.0)
Requires-Dist: plotly (>=5.15.0,<6.0.0)
Requires-Dist: statsmodels (>=0.14.0,<0.15.0)
Requires-Dist: typer[all] (>=0.9.0,<0.10.0)
Requires-Dist: waitress (>=2.1.2,<3.0.0)
